README.rst
setup.py
light/__init__.py
light/cache.py
light/configuration.py
light/constant.py
light/crypto.py
light/helper.py
light/i18n.py
light/job.py
light/log.py
light/validator.py
light/error/__init__.py
light/error/db.py
light/error/http.py
light/http/__init__.py
light/http/context.py
light/http/dispatcher.py
light/http/loader.py
light/http/middleware.py
light/http/response.py
light/http/unparam.py
light/http/websocket.py
light/model/__init__.py
light/model/data.py
light/model/datamigrate.py
light/model/datarider.py
light/model/file.py
light/model/structure.py
light/model/user.py
light/mongo/__init__.py
light/mongo/controller.py
light/mongo/define.py
light/mongo/encoder.py
light/mongo/mapping.py
light/mongo/model.py
light/mongo/operator.py
light/mongo/session.py
light/mongo/type.py
light/validate/__init__.py
light/validate/define.py
light/validate/rule.py
light/validate/sanitizer.py
light/validate/validator.py
light_core.egg-info/PKG-INFO
light_core.egg-info/SOURCES.txt
light_core.egg-info/dependency_links.txt
light_core.egg-info/requires.txt
light_core.egg-info/top_level.txt
tests/__init__.py
tests/test_cache.py
tests/test_configuration.py
tests/test_crypto.py
tests/test_helper.py
tests/test_job.py
tests/test_validator.py
tests/http/__init__.py
tests/http/test_context.py
tests/http/test_dispatcher.py
tests/http/test_loader.py
tests/model/__init__.py
tests/model/test_data.py
tests/model/test_datarider.py
tests/model/test_file.py
tests/model/test_user.py
tests/mongo/__init__.py
tests/mongo/test_encoder.py
tests/mongo/test_mapping.py
tests/mongo/test_model.py
tests/mongo/test_type.py
tests/validate/__init__.py
tests/validate/test_rule.py
tests/validate/test_sanitizer.py
tests/validate/test_validator.py