Metadata-Version: 1.1
Name: light-core
Version: 0.3.0
Summary: Light Core for Python
Home-page: https://github.com/LightCircle/LightCorePy
Author: Alphabets
Author-email: r2space@gmail.com
License: MIT
Keywords: light core
Platform: UNKNOWN
Classifier: Development Status :: 4 - Beta
Classifier: Intended Audience :: Developers
Classifier: Topic :: Software Development :: Build Tools
Classifier: License :: OSI Approved :: MIT License
Classifier: Programming Language :: Python :: 3.5
Classifier: Programming Language :: Python :: 3.6
